pdfchain/__init__.py
pdfchain/__main__.py
pdfchain/app.py
pdfchain/cli.py
pdfchain/cmd_colors.py
pdfchain/cmd_pdftk.py
pdfchain/cmd_pdftk_ORG.py
pdfchain/filechooser.py
pdfchain/main.py
pdfchain/paths.py
pdfchain/preferences.py
pdfchain/strings.py
pdfchain/window.py
pdfchain/window_ORG.py
pdfchain-0.5.0.0a5.data/data/share/applications/pdfchain.desktop
pdfchain-0.5.0.0a5.data/data/share/icons/hicolor/128x128/apps/pdfchain.png
pdfchain-0.5.0.0a5.data/data/share/icons/hicolor/16x16/apps/pdfchain.png
pdfchain-0.5.0.0a5.data/data/share/icons/hicolor/192x192/apps/pdfchain.png
pdfchain-0.5.0.0a5.data/data/share/icons/hicolor/22x22/apps/pdfchain.png
pdfchain-0.5.0.0a5.data/data/share/icons/hicolor/24x24/apps/pdfchain.png
pdfchain-0.5.0.0a5.data/data/share/icons/hicolor/256x256/apps/pdfchain.png
pdfchain-0.5.0.0a5.data/data/share/icons/hicolor/32x32/actions/pdfchain-concatenate.png
pdfchain-0.5.0.0a5.data/data/share/icons/hicolor/32x32/actions/pdfchain-stamp.png
pdfchain-0.5.0.0a5.data/data/share/icons/hicolor/32x32/apps/pdfchain.png
pdfchain-0.5.0.0a5.data/data/share/icons/hicolor/48x48/apps/pdfchain.png
pdfchain-0.5.0.0a5.data/data/share/icons/hicolor/64x64/apps/pdfchain.png
pdfchain-0.5.0.0a5.data/data/share/icons/hicolor/96x96/apps/pdfchain.png
pdfchain-0.5.0.0a5.data/data/share/locale/.keep
pdfchain-0.5.0.0a5.data/data/share/pdfchain/ui/dialogs.ui
pdfchain-0.5.0.0a5.data/data/share/pdfchain/ui/menus.ui
pdfchain-0.5.0.0a5.data/data/share/pdfchain/ui/window.ui
pdfchain-0.5.0.0a5.data/data/share/pixmaps/pdfchain.png
pdfchain-0.5.0.0a5.dist-info/LICENSE.md
pdfchain-0.5.0.0a5.dist-info/METADATA
pdfchain-0.5.0.0a5.dist-info/WHEEL
pdfchain-0.5.0.0a5.dist-info/entry_points.txt
pdfchain-0.5.0.0a5.dist-info/top_level.txt
pdfchain-0.5.0.0a5.dist-info/RECORD
