Metadata-Version: 2.1
Name: pdfchain
Version: 0.5.0.0.alpha.5
Summary: A graphical user interface for the PDF Toolkit
Home-page: https://pdfchain.sourceforge.io/
Author: Martin Singer
Author-email: martin.singer@web.de
License: GPLv3+
Download-URL: https://sourceforge.net/p/pdfchain/neo/ci/master/tree/
Keywords: PDF
Platform: UNKNOWN
Classifier: Development Status :: 3 - Alpha
Classifier: Environment :: X11 Applications :: GTK
Classifier: Intended Audience :: End Users/Desktop
Classifier: License :: OSI Approved :: GNU General Public License v3 or later (GPLv3+)
Classifier: Operating System :: POSIX
Classifier: Topic :: Office/Business
Classifier: Programming Language :: Python :: 3
Requires-Python: >=3.6
